arc_file_extractor/__init__.py
arc_file_extractor/__main__.py
arc_file_extractor/arc_file_extractor.py
arc_file_extractor/cli.py
arc_file_extractor/utils.py
arc_file_extractor-0.1.0.dist-info/licenses/LICENSE
arc_file_extractor-0.1.0.dist-info/METADATA
arc_file_extractor-0.1.0.dist-info/WHEEL
arc_file_extractor-0.1.0.dist-info/entry_points.txt
arc_file_extractor-0.1.0.dist-info/top_level.txt
arc_file_extractor-0.1.0.dist-info/RECORD
