Metadata-Version: 2.4
Name: arc_file_extractor
Version: 0.1.0
Summary: CLI frontend for unified file extraction on UNIX systems.
Author-email: Pedro Henrique Alves <nukhes@protonmail.com>
Maintainer-email: Pedro Henrique Alves <nukhes@protonmail.com>
License-Expression: GPL-3.0
Project-URL: homepage, https://github.com/nukhes/arc_file_extractor
Project-URL: repository, https://github.com/nukhes/arc_file_extractor
Project-URL: bugs, https://github.com/nukhes/arc_file_extractor/issues
Project-URL: changelog, https://github.com/nukhes/arc_file_extractor/blob/master/HISTORY.rst
Project-URL: documentation, https://arc-file-extractor.readthedocs.io
Keywords: archive,compression,extraction,cli,zip,tar,gzip
Classifier: Development Status :: 4 - Beta
Classifier: Intended Audience :: Developers
Classifier: Intended Audience :: System Administrators
Classifier: Operating System :: POSIX
Classifier: Operating System :: Unix
Classifier: Programming Language :: Python :: 3
Classifier: Programming Language :: Python :: 3.8
Classifier: Programming Language :: Python :: 3.9
Classifier: Programming Language :: Python :: 3.10
Classifier: Programming Language :: Python :: 3.11
Classifier: Programming Language :: Python :: 3.12
Classifier: Topic :: System :: Archiving :: Compression
Classifier: Topic :: Utilities
Classifier: Topic :: Software Development :: Libraries :: Python Modules
Classifier: Environment :: Console
Requires-Python: >=3.8
License-File: LICENSE
Requires-Dist: typer[all]>=0.9.0
Requires-Dist: rich>=13.0.0
Provides-Extra: dev
Requires-Dist: coverage; extra == "dev"
Requires-Dist: mypy; extra == "dev"
Requires-Dist: pytest; extra == "dev"
Requires-Dist: ruff; extra == "dev"
Requires-Dist: tox; extra == "dev"
Dynamic: license-file
